rabbit_droppings/__init__.py
rabbit_droppings/message.py
rabbit_droppings/pika_message.py
rabbit_droppings/queue.py
rabbit_droppings/rabbit.py
rabbit_droppings/rabbit_config.py
rabbit_droppings/reader.py
rabbit_droppings/writer.py
rabbit_utils-0.1.0.data/scripts/rabbit_droppings
rabbit_utils-0.1.0.dist-info/LICENSE
rabbit_utils-0.1.0.dist-info/METADATA
rabbit_utils-0.1.0.dist-info/WHEEL
rabbit_utils-0.1.0.dist-info/top_level.txt
rabbit_utils-0.1.0.dist-info/RECORD
